xml_to_dict/__init__.py
xml_to_dict/xml_to_dict.py
xml_to_dict-0.1.6.dist-info/LICENSE
xml_to_dict-0.1.6.dist-info/METADATA
xml_to_dict-0.1.6.dist-info/WHEEL
xml_to_dict-0.1.6.dist-info/top_level.txt
xml_to_dict-0.1.6.dist-info/RECORD
