Metadata-Version: 2.1
Name: xml-to-dict
Version: 0.1.6
Summary: A simple Python XML to Dictionary parser
Home-page: https://github.com/xthehatterx/xml_to_dict
Author: Ezequiel M. Iglesias
Author-email: ezequiel.m.iglesias@gmail.com
License: MIT
Platform: UNKNOWN
Classifier: Programming Language :: Python :: 3
Classifier: License :: OSI Approved :: MIT License
Classifier: Operating System :: OS Independent
Requires-Python: >=3.6
